snel.py
snel-0.0.1.dist-info/METADATA
snel-0.0.1.dist-info/WHEEL
snel-0.0.1.dist-info/entry_points.txt
snel-0.0.1.dist-info/top_level.txt
snel-0.0.1.dist-info/RECORD
